LISENSE
MANIFEST.in
README.rst
__init__.py
setup.py
std_test.py
testpack.egg-info/PKG-INFO
testpack.egg-info/SOURCES.txt
testpack.egg-info/dependency_links.txt
testpack.egg-info/top_level.txt