Metadata-Version: 1.0
Name: testpack
Version: 0.0.6
Summary: Testing  PYPI APP
Home-page: https://sites.google.com/site/rohitgbal/
Author: Rohit G Bal
Author-email: rohitgbal@gmail.com
License: MIT
Platform: UNKNOWN
